customer_analysis.py
customer_analysis_tikhonmakeev-0.1.dist-info/METADATA
customer_analysis_tikhonmakeev-0.1.dist-info/WHEEL
customer_analysis_tikhonmakeev-0.1.dist-info/entry_points.txt
customer_analysis_tikhonmakeev-0.1.dist-info/top_level.txt
customer_analysis_tikhonmakeev-0.1.dist-info/RECORD
