Metadata-Version: 2.1
Name: customer_analysis_tikhonmakeev
Version: 0.1
Requires-Python: >=3.8
Requires-Dist: pandas
